linkedit/__init__.py
linkedit-1.1.3.dist-info/LICENSE
linkedit-1.1.3.dist-info/METADATA
linkedit-1.1.3.dist-info/WHEEL
linkedit-1.1.3.dist-info/top_level.txt
linkedit-1.1.3.dist-info/RECORD
