Metadata-Version: 2.1
Name: linkedit
Version: 1.1.3
Summary: Sophisticate Linked List
Home-page: https://pypi.org/project/linkedit/
Author: khiat Mohammed Abderrezzak
Author-email: khiat.dev@gmail.com
License: MIT
Keywords: linked list
Classifier: Programming Language :: Python :: 3
Classifier: Operating System :: OS Independent
Classifier: License :: OSI Approved :: MIT License
Requires-Python: >=3.6
License-File: LICENSE
Requires-Dist: tabulate (>=0.9.0)
